odoo8_addon_base_user_reset_access-8.0.1.0.0.99.dev20-nspkg.pth
odoo_addons/base_user_reset_access/README.rst
odoo_addons/base_user_reset_access/__init__.py
odoo_addons/base_user_reset_access/__openerp__.py
odoo_addons/base_user_reset_access/i18n/ar.po
odoo_addons/base_user_reset_access/i18n/base_user_reset_access.pot
odoo_addons/base_user_reset_access/i18n/ca.po
odoo_addons/base_user_reset_access/i18n/da.po
odoo_addons/base_user_reset_access/i18n/de.po
odoo_addons/base_user_reset_access/i18n/el_GR.po
odoo_addons/base_user_reset_access/i18n/es.po
odoo_addons/base_user_reset_access/i18n/es_ES.po
odoo_addons/base_user_reset_access/i18n/fi.po
odoo_addons/base_user_reset_access/i18n/fr.po
odoo_addons/base_user_reset_access/i18n/fr_CH.po
odoo_addons/base_user_reset_access/i18n/hr.po
odoo_addons/base_user_reset_access/i18n/hr_HR.po
odoo_addons/base_user_reset_access/i18n/it.po
odoo_addons/base_user_reset_access/i18n/nl.po
odoo_addons/base_user_reset_access/i18n/pt_BR.po
odoo_addons/base_user_reset_access/i18n/sl.po
odoo_addons/base_user_reset_access/i18n/tr.po
odoo_addons/base_user_reset_access/i18n/tr_TR.po
odoo_addons/base_user_reset_access/i18n/zh_CN.po
odoo_addons/base_user_reset_access/models/__init__.py
odoo_addons/base_user_reset_access/models/res_users.py
odoo_addons/base_user_reset_access/static/description/icon.png
odoo_addons/base_user_reset_access/tests/__init__.py
odoo_addons/base_user_reset_access/tests/test_base_user_reset_access.py
odoo_addons/base_user_reset_access/views/ir_ui_menu.xml
odoo_addons/base_user_reset_access/views/res_users_view.xml
odoo8_addon_base_user_reset_access-8.0.1.0.0.99.dev20.dist-info/METADATA
odoo8_addon_base_user_reset_access-8.0.1.0.0.99.dev20.dist-info/WHEEL
odoo8_addon_base_user_reset_access-8.0.1.0.0.99.dev20.dist-info/namespace_packages.txt
odoo8_addon_base_user_reset_access-8.0.1.0.0.99.dev20.dist-info/top_level.txt
odoo8_addon_base_user_reset_access-8.0.1.0.0.99.dev20.dist-info/RECORD
